<?xml version="1.0" encoding="UTF-8"?>
<!DOCTYPE suite SYSTEM "https://testng.org/testng-1.0.dtd">
<suite name="Suite 2" thread-count="4" parallel="tests" >
    <listeners>
        <listener class-name="extentReportListener.TestNGListener"></listener>
    </listeners>
    <test name="Practice Auto in AT.in">
        <parameter name="url" value="https://practice.automationtesting.in/"/>
        <classes>
            <class name="wikipedia.testsuites.PracticeTest">
            </class>
        </classes>
    </test>
</suite>
